ocr_json_processor/__init__.py
ocr_json_processor/common.py
ocr_json_processor/extractor.py
ocr_json_processor/json_updater.py
ocr_json_processor/main.py
ocr_json_processor/ocr_service.py
ocr_json_processor/openai_test_json.py
ocr_json_processor/test.py
ocr_json_processor/utils.py
tests/__init__.py
tests/test_json_updater.py
tests/test_ocr_service.py
tests/test_utils.py
ocr_json_processor-0.1.0.dist-info/LICENSE
ocr_json_processor-0.1.0.dist-info/METADATA
ocr_json_processor-0.1.0.dist-info/WHEEL
ocr_json_processor-0.1.0.dist-info/top_level.txt
ocr_json_processor-0.1.0.dist-info/RECORD
