Metadata-Version: 2.1
Name: ocr-json-processor
Version: 0.1.0
Summary: A Python package for OCR response processing and JSON updates.
Author: Shubham Kumar
Author-email: Shubham Kumar <shubham@perfecter.ai>
License: MIT License
Project-URL: Source, https://github.com/velocius-ailabs/ocr-json-processor
Keywords: OCR,JSON,confidence scores,text extraction
Classifier: Programming Language :: Python :: 3
Classifier: License :: OSI Approved :: MIT License
Classifier: Operating System :: OS Independent
License-File: LICENSE
Requires-Dist: Pillow
Requires-Dist: numpy
Requires-Dist: python-dotenv
Requires-Dist: azure-core
Requires-Dist: azure-ai-documentintelligence==1.0.0b2
Requires-Dist: amazon-textract-textractor==1.7.10
Requires-Dist: PyMuPDF
Requires-Dist: pytest
Requires-Dist: fastapi
Requires-Dist: fuzzywuzzy
